tresoryx/__init__.py
tresoryx/auto_bilan.py
tresoryx/auto_dette.py
tresoryx/auto_exercice.py
tresoryx/communs.py
tresoryx/datajoueur.py
tresoryx/fusionne_dettes.py
Tresoryx-0.2.0.dist-info/COPYING
Tresoryx-0.2.0.dist-info/METADATA
Tresoryx-0.2.0.dist-info/WHEEL
Tresoryx-0.2.0.dist-info/entry_points.txt
Tresoryx-0.2.0.dist-info/top_level.txt
Tresoryx-0.2.0.dist-info/RECORD
