Metadata-Version: 2.1
Name: Tresoryx
Version: 0.2.0
Summary: Humble automatisations for treasury using spreadsheets.
Home-page: https://gitlab.com/GullumLuvl/tresoryx
Author: Guitou des Phoenix
Author-email: guitou.phoenix@mailo.com
License: GPLv3
Platform: UNKNOWN
Classifier: Development Status :: 3 - Alpha
Classifier: License :: OSI Approved :: GNU General Public License v3 (GPLv3)
Classifier: Natural Language :: French
Classifier: Programming Language :: Python :: 3.5
Classifier: Topic :: Utilities
Requires-Dist: PyYAML
Requires-Dist: numpy
Requires-Dist: openpyxl
Requires-Dist: pandas
Requires-Dist: xlrd
Requires-Dist: xlwt
Provides-Extra: graph
Requires-Dist: matplotlib ; extra == 'graph'
Provides-Extra: xlsx_style
Requires-Dist: jinja2 ; extra == 'xlsx_style'
